tmprofile/__init__.py
tmprofile/tmprofile.py
tmprofile-0.0.5.dist-info/LICENSE
tmprofile-0.0.5.dist-info/METADATA
tmprofile-0.0.5.dist-info/WHEEL
tmprofile-0.0.5.dist-info/top_level.txt
tmprofile-0.0.5.dist-info/RECORD
