Metadata-Version: 2.1
Name: tmprofile
Version: 0.0.5
Summary: A simple time, ram & vram python profiler.
Author-email: Luc Vedrenne <vedrenneluc@gmail.com>
Project-URL: Homepage, https://github.com/ListIndexOutOfRange/tmprofile
Project-URL: Issues, https://github.com/ListIndexOutOfRange/tmprofile/issues
Classifier: Programming Language :: Python :: 3
Classifier: License :: OSI Approved :: MIT License
Classifier: Operating System :: OS Independent
Requires-Python: >=3.8
License-File: LICENSE
Requires-Dist: numpy
Requires-Dist: matplotlib
Requires-Dist: psutil
Requires-Dist: prettytable
Requires-Dist: nvidia-ml-py3
